AUTHORS
CREDITS
LICENSE.txt
MANIFEST.in
README.md
UPDATES
setup.cfg
setup.py
django_userpure.egg-info/PKG-INFO
django_userpure.egg-info/SOURCES.txt
django_userpure.egg-info/dependency_links.txt
django_userpure.egg-info/not-zip-safe
django_userpure.egg-info/requires.txt
django_userpure.egg-info/top_level.txt
userpure/__init__.py
userpure/__init__.pyc
userpure/managers.py
userpure/models.py
userpure/path.pyc
userpure/project.pyc
userpure/settings.py
userpure/tests.py