Metadata-Version: 1.0
Name: django-userpure
Version: 0.1.0
Summary: Basic user proerties and user ability for django 1.5.
Home-page: https://github.com/abec/django-userpure
Author: Abraham Elmahrek
Author-email: abraham@elmahrek.com
License: UNKNOWN
Download-URL: https://github.com/abec/django-userpure/tarball/0.1
Platform: UNKNOWN
Classifier: Development Status :: 1 - Planning
Classifier: Environment :: Web Environment
Classifier: Framework :: Django
Classifier: Intended Audience :: Developers
Classifier: License :: OSI Approved :: BSD License
Classifier: Operating System :: OS Independent
Classifier: Programming Language :: Python
Classifier: Topic :: Software Development :: Libraries
